Metadata-Version: 1.1
Name: tiffreader
Version: 0.1.1
Summary: convenience wrapper for libtiff
Home-page: https://github.com/Palpatineli/tiffreader
Author: Keji Li
Author-email: mail@keji.li
License: GPLv3
Download-URL: https://github.com/Palpatineli/tiffreader/archive/0.1.1.tar.gz
Platform: UNKNOWN
Classifier: Development Status :: 4 - Beta
Classifier: Programming Language :: Python :: 3
